{"version":1,"resource":"file:///home/sauron/.config/picom/picom.conf","entries":[{"id":"YSKV.conf","timestamp":1703808962823},{"id":"xTqY.conf","timestamp":1703808976723},{"id":"ULJ4.conf","timestamp":1703809016890},{"id":"425f.conf","timestamp":1703809098650},{"id":"9o7R.conf","timestamp":1703809131373},{"id":"glzO.conf","timestamp":1703809153533},{"id":"yL1v.conf","timestamp":1703809168833},{"id":"CieK.conf","timestamp":1703809184090},{"id":"tjKR.conf","timestamp":1703809287500},{"id":"WaAq.conf","timestamp":1703809604057},{"id":"6HQX.conf","timestamp":1703809733947},{"id":"TXKx.conf","timestamp":1703809762087},{"id":"VAKA.conf","timestamp":1703809905683},{"id":"kgWS.conf","timestamp":1703809918130},{"id":"HGHE.conf","timestamp":1703809952880},{"id":"VwLy.conf","timestamp":1703809965533},{"id":"n830.conf","timestamp":1703809981290},{"id":"QT3j.conf","timestamp":1703810031597},{"id":"XyDu.conf","timestamp":1703910005153},{"id":"17FM.conf","timestamp":1703910100420},{"id":"sil0.conf","timestamp":1703910125293},{"id":"qr89.conf","timestamp":1703910149300}]}